<?xml version='1.0' encoding='UTF-8'?>
<file>
  <metadata id="10460" id_hbbw="425" id_irg_sort="425" id_sort="104250"/>
  <letter>
    <s translated="true" n="1" original_language="la" original_no_xml="Admonere quoque te volo, observandissime vir, ut diligenter perpendas Capitonis argumentum, quo putat nullo negotio stringendos Arrios.">Ich möchte dich auch ermahnen, hochverehrter Herr, dass du den Beweis Capitos sorgfältig erwägst, bei dem er glaubt, dass die Arrios in keiner Angelegenheit verstrickt werden sollten.</s>
    <s translated="true" n="2" original_language="la" original_no_xml="Primo argumentatur, ni fallor, a creatione.">Das erste Argument ist, wenn ich mich nicht irre, von der Erschaffung.</s>
    <s translated="true" n="3" original_language="la" original_no_xml="Non negant Arrii per Christum omnia condita, sed Christum omnia condidisse non admittent, nec sequetur: Per Christum omnia condita sunt. ergo ipse ille deus conditor.">Die Arianer leugnen nicht, dass alles durch Christus geschaffen ist, sondern dass Christus alles geschaffen hat, und es folgt nicht: "Durch Christus ist alles geschaffen", also jener Gott, der Schöpfer.</s>
    <s translated="true" n="4" original_language="la" original_no_xml="Secundo putat Arrianis partes accusatoris permittendas urgendosque, ut negativam hanc probent, Christum non esse deum.">Zweitens meint er, die Rolle des Anklägers müsse man bedrängen, um zu beweisen, dass dies eine negative sei, dass Christus nicht Gott sei.</s>
    <s translated="true" n="5" original_language="la" original_no_xml="Hic memineris rarissime iure cogi quemquam, ut negativam probet.">Erinnerst du dich daran, dass jemand mit einem sehr seltenen Recht gezwungen wird, wie er die negativen Beweise beweist.</s>
    <s translated="true" n="6" original_language="la" original_no_xml="Magis aequum et iustum est nos probare, quod affirmamus, deinde nos quoque manere accusatores.">Es ist gerechter und gerechter, zu beweisen, was wir behaupten, dass auch wir Ankläger bleiben.</s>
    <s translated="true" n="7" original_language="la" original_no_xml="Quodsi accusatoris partes volumus in reos reiicere, forte videbimur caussae nostre non per omnia fidere eamque parum esse stabilem suspicari.">Wenn wir aber die Rolle des Anklägers gegen die Angeklagten ablehnen wollen, werden wir vielleicht der Meinung sein, dass unsere Sache nicht in allen Dingen vermutet, dass sie wenig standhaft ist.</s>
    <s translated="true" n="8" original_language="la" original_no_xml="Literas lectas rogo ut remittas.">Ich bitte dich, die Briefe zurückzuschicken.</s>
    <s translated="true" n="9" original_language="la" original_no_xml="Vale et da veniam, quod te adeo crudis literis obtundo.">Leb wohl und gib es mir, dass ich dich so grausamen Briefen zusage.</s>
    <s translated="true" n="10" original_language="la" original_no_xml="Bullingero.">Bullinger.</s>
  </letter>
</file>
