<?xml version='1.0' encoding='UTF-8'?>
<file>
  <metadata id="10836" id_hbbw="797" id_irg_sort="797" id_sort="107970"/>
  <letter>
    <s translated="true" n="1" original_language="la" original_no_xml="S.">Ich grüsse Dich</s>
    <s translated="true" n="2" original_language="la" original_no_xml="Vos adit Angelus Italus, qui contubernalis fuit et auditor Bucero toto biennio, homo eruditus atque egregie pius, quem vobis commendo.">Euch kommt ein italienischer Engel, der ein Gefährte und ein Hörer Bucers seit zwei Jahren war, ein gelehrter und vortrefflich frommer Mann, den ich euch empfehle.</s>
    <s translated="true" n="3" original_language="la" original_no_xml="Neque aliud efflagito, quam ut quisque illi copiam sui prębeat.">Ich bitte dich nicht, ihm etwas anderes zu geben, als dass jeder ihm eine selbständige Fülle anbietet.</s>
    <s translated="true" n="4" original_language="la" original_no_xml="Nam appellandi consalutandique vos percupidus est.">Denn er ist sehr begierig, euch zu grüssen.</s>
    <s translated="true" n="5" original_language="la" original_no_xml="Facietis in hoc officium charitatis atque adeo humanitatis, quę cum in ethnicis regnet, plurimum apud nos christianos vigere debet.">Ihr werdet in dieser Aufgabe der Nächstenliebe und so der Menschlichkeit tun, die, wenn sie in den Heiden herrscht, bei uns Christen am meisten gedeihen muss.</s>
    <s translated="true" n="6" original_language="la" original_no_xml="Hodie, mi Bullingere, de conventu Saxonico.">Heute, mein Bullinger, über das sächsische Treffen.</s>
    <s translated="true" n="7" original_language="la" original_no_xml="Aestus magnus, iter prolixum, corpus invalidum et affectum, et tamen adibo sospitante me Christo, quae mea forte postrema profectio erit.">Ein grosser Sommer, eine lange Reise, ein starker und begehrender Leib, und doch werde ich mit Christus umherschweifen, der vielleicht mein letzter Weg sein wird.</s>
    <s translated="true" n="8" original_language="la" original_no_xml="Interim ora tu dominum, ut pro ecclesiarum concordia faciat, quod animo, deus novit, syncero publiceque de ecclesiis benemereri cupiente admoliamur.">In der Zwischenzeit bete du zum Herrn, dass er für die Eintracht der Kirchen tut, was Gott im Geiste weiss, und dass wir öffentlich mit dem aufrichtigen Wunsch nach Wohlergehen über die Kirchen hinrichten.</s>
    <s translated="true" n="9" original_language="la" original_no_xml="Amicas ac generales literas proxime ad nos scribe, quibus in utilitatem ecclesiarum per occasionem utamur.">Schreibe uns bald freundliche und allgemeine Briefe, in denen wir uns bei Gelegenheit zum Nutzen der Kirchen bedienen.</s>
    <s translated="true" n="10" original_language="la" original_no_xml="Neque tamen causae, obsecro te, memineris.">Und doch wirst du dich nicht an die Ursache erinnern, ich bitte dich.</s>
    <s translated="true" n="11" original_language="la" original_no_xml="Pellicano et Bibliandro hunc virum egregium similiter tecum commendo, cui pateris has facere communes.">Ich empfehle diesen vortrefflichen Mann Pellicano und Bibliander ähnlich mit dir, dem du väterst, diese Dinge gemeinsam zu tun.</s>
    <s translated="true" n="12" original_language="la" original_no_xml="Vale.">Leb wohl.</s>
    <s translated="true" n="13" original_language="la" original_no_xml="18. aprilis anno 1536.">18. April 1536.</s>
    <s translated="true" n="14" original_language="la" original_no_xml="V. Capito.">V. Capito.</s>
    <s translated="true" n="15" original_language="la" original_no_xml="M. Henrico Bullingero, Pellicano et Bibliandro, viris eruditissimis, sibi in domino observandis.">M. Heinrich Bullinger, Pellicano und Bibliander, sehr gelehrte Männer, die ihm im Herrn zu beobachten sind.</s>
  </letter>
</file>
