<?xml version='1.0' encoding='UTF-8'?>
<file>
  <metadata id="11654" id_hbbw="1611" id_irg_sort="1611" id_sort="116110"/>
  <letter>
    <s translated="true" n="1" original_language="la" original_no_xml="Gratiam et vitae innocentiam a Domino.">Danke und das unschuldige Leben vom Herrn!</s>
    <s translated="true" n="2" original_language="la" original_no_xml="Literas ad te dederam his diebus, amantissime Bullingere, per Rudolphum Schintium; an redditae sint, non constat.">Ich hatte dir in diesen Tagen, lieber Bullinger, einen Brief über Rudolf Schintius geschickt; ob er zurückgesandt wurde, ist nicht bekannt.</s>
    <s translated="true" n="3" original_language="la" original_no_xml="Illud vero potissimum est, quod continent, ut Bullingeri commentarios in omnes divi Patli epistolas ceterasque cononicas in forma maiori, codice eleganter illigato apud te invenirem.">Vor allem aber ist das, was sie enthalten, dass ich Bullingers Kommentare zu allen übrigen, in einer grösseren Form angefertigten, eleganten Handschrift bei Ihnen finde.</s>
    <s translated="true" n="4" original_language="la" original_no_xml="Coronatum et batzium mitto; si quid defuerit, sine dilatione quoque mittam.">Ich sende Kronat und Batzius; wenn etwas fehlt, werde ich es auch ohne Verzögerung schicken.</s>
    <s translated="true" n="5" original_language="la" original_no_xml="Praesentium latori tuto committere poteris librum, - probe enim curabit, ut integre ad me veniat -, et si usu venerit, ut tibi servire vel in aliqua re prodesse potuero, iubeto.">Ich bitte dich, dem gegenwärtigen Überbringer ein sicheres Buch anvertrauen zu können, denn er wird sich bemühen, es ganz und gar zu mir zu kommen, und wenn er von Nutzen ist, werde ich es dir befehlen, dir zu dienen oder in irgendeiner Sache nützen zu können.</s>
    <s translated="true" n="6" original_language="la" original_no_xml="Vale.">Leb wohl.</s>
    <s translated="true" n="7" original_language="la" original_no_xml="Ex Rhetiae Curia, 6. Martii 42. Salvos optamus omnes fratres.">Aus der Kurie von Rhetia, 6. März 42. Ich wünsche allen Brüdern Gesundheit.</s>
    <s translated="true" n="8" original_language="la" original_no_xml="Pro nobis orate; nam in periculo sumus haud exiguo vel negligendo.">Betet für uns; denn wir sind in Gefahr, ohne etwas zu gering oder zu wenig zu vernachlässigen.</s>
    <s translated="true" n="9" original_language="la" original_no_xml="Tuus Ioannes Comander.">Dein Johannes Comander.</s>
    <s translated="true" n="10" original_language="la" original_no_xml="Pietate et doctrina spectabili viro magistro Heinricho Ballingero, domino ac fratri suo observando.">An einen bemerkenswerten Meister Heinrich Ballinger, seinem beobachtenden Herrn und Bruder.</s>
    <s translated="false" n="11" original_language="de" original_no_xml="Meister Heinrichen Bullinger."/>
  </letter>
</file>
