<?xml version='1.0' encoding='UTF-8'?>
<file>
  <metadata id="12030" id_hbbw="1983" id_irg_sort="1983" id_sort="119830"/>
  <letter>
    <s translated="true" n="1" original_language="la" original_no_xml="Eruditissime vir et domine mi observandissime.">Der gelehrte Mann und mein hochverehrter Herr.</s>
    <s translated="true" n="2" original_language="la" original_no_xml="Vidi, quę heri ad me scripsisti, et omnia libenter intellexi, quia mihi satisfecisti, ut desiderabam.">Ich habe gesehen, was du mir gestern geschrieben hast, und ich habe alles gerne verstanden, weil du mir genug getan hast, wie ich es mir wünschte.</s>
    <s translated="true" n="3" original_language="la" original_no_xml="Quare fateor me tibi plurimum debere et ago gratias, ac quicquid possum et habeo, id totum tibi offero.">Deshalb gebe ich zu, dass ich dir am meisten schulde und danke, und was immer ich kann und habe, biete ich dir das Ganze an.</s>
    <s translated="true" n="4" original_language="la" original_no_xml="Tuos salutavi, ut iussisti, qui te pariter resalutant.">Ich habe deine Freunde gegrüsst, wie du es befohlen hast, die dich ebenfalls grüssen.</s>
    <s translated="true" n="5" original_language="la" original_no_xml="Ego vero non ero immemor tuę comendationis erga tuos, ubi eis prodesse potero, ut hactenus feci.">Ich aber werde nicht an deine Empfehlung an deine Freunde denken, wenn ich ihnen nützen kann, wie ich es bisher getan habe.</s>
    <s translated="true" n="6" original_language="la" original_no_xml="Nihil aliud habeo, quod scribam, nisi quod more solito tuus sum et superi me genuere tuum, cui ac familię toto corde me comendo.">Ich weiss nichts anderes, was ich schreiben könnte, als dass ich in gewohnter Weise dein bin und deine Götter mich zeugen, dem ich und meine Familie mit ganzem Herzen empfehle.</s>
    <s translated="true" n="7" original_language="la" original_no_xml="Brengartii, 12. septembris 1544.">Brengartii, 12. September 1544.</s>
    <s translated="true" n="8" original_language="la" original_no_xml="Totus tuus Io. Dominicus">Io. Dominicus, ganz der Deine.</s>
    <s translated="true" n="9" original_language="la" original_no_xml="Panizonus.">Panizon.</s>
    <s translated="true" n="10" original_language="la" original_no_xml="Eruditissimo viro ac domino meo observandissimo d. Henrico Bullingero.">An meinen höchst gelehrten und aufmerksamen Herrn Heinrich Bullinger.</s>
    <s translated="true" n="11" original_language="la" original_no_xml="Turregi.">Zürich.</s>
  </letter>
</file>
