<?xml version='1.0' encoding='UTF-8'?>
<file>
  <metadata id="12227" id_hbbw="2180" id_irg_sort="2180" id_sort="121800"/>
  <letter>
    <s translated="true" n="1" original_language="la" original_no_xml="S[alutem] d[ico].">Ich grüsse Dich.</s>
    <s translated="true" n="2" original_language="la" original_no_xml="Scio pios et studiosos tuae humanitati, domine et frater colende idemque mihi dilectissime, alias commendatos esse.">Ich weiss, dass deine frommen und ergebenen Menschen, mein Herr und verehrter Bruder, mir auch das Gleiche empfehlen.</s>
    <s translated="true" n="3" original_language="la" original_no_xml="Quia tamen multi errones saepe bonis viris imponunt, dum se venditant pro studiosis, cum sint nebulones, volui huic d. Gerhardo Frisio testimonium dare fidele, ne inter errones numeretur.">Weil aber viele Irrtümer sich oft guten Männern aufdrängen, während sie sich für die Studenten verkaufen, da sie Schurke sind, wollte ich diesem Herrn Gerhard Frisius ein zuverlässiges Zeugnis geben, damit er nicht unter den Irrtümern gezählt wird.</s>
    <s translated="true" n="4" original_language="la" original_no_xml="Est hic honesto loco et nobili familia natus, natione Frisius.">Hier ist ein ehrlicher Ort und eine edle Familie, aus Frisius.</s>
    <s translated="true" n="5" original_language="la" original_no_xml="Venit ad nos Tigurum pietatis et literarum ergo.">Er kam also zu uns nach Zürich mit Frömmigkeit und Briefen.</s>
    <s translated="true" n="6" original_language="la" original_no_xml="Egit in aedibus d. Pellicani.">Er hat im Haus des Herrn Pelikan gehandelt.</s>
    <s translated="true" n="7" original_language="la" original_no_xml="Pius est et doctus.">Er ist fromm und gelehrt.</s>
    <s translated="true" n="8" original_language="la" original_no_xml="Rediturus autem domum et in patriam voluit prius videre te et ecclesiam urbemque vestram.">Er wollte aber nach Hause und in sein Vaterland zurückkehren, um dich und deine Stadt zuerst zu sehen.</s>
    <s translated="true" n="9" original_language="la" original_no_xml="Opulentus est.">Er ist reich.</s>
    <s translated="true" n="10" original_language="la" original_no_xml="Subsidio non indiget.">Er braucht keine Hilfe.</s>
    <s translated="true" n="11" original_language="la" original_no_xml="Excipe ergo illum, obsecro, uti dignus est.">Nimm ihn also auf, ich bitte dich, wie er würdig ist.</s>
    <s translated="true" n="12" original_language="la" original_no_xml="Hac re facies rem te dignam et mihi longe gratissimam; mire enim a nobis omnibus amatur propter pietatem, candorem et eruditionem.">In dieser Angelegenheit wirst du eine Sache tun, die dir würdig ist und die mir sehr erfreulich ist; denn es ist wunderbar, dass er von uns allen wegen seiner Frömmigkeit, Offenheit und Gelehrsamkeit geliebt wird.</s>
    <s translated="true" n="13" original_language="la" original_no_xml="Vive et vale!">Lebe wohl!</s>
    <s translated="true" n="14" original_language="la" original_no_xml="Tiguri, 16. iunii anno 1545.">Zürich, 16. Juni 1545.</s>
    <s translated="true" n="15" original_language="la" original_no_xml="Literas d. Laeti tuis coniunctas accepi et ago tibi gratias.">Ich habe den gemeinsamen Brief des Herrn erhalten und danke dir.</s>
    <s translated="true" n="16" original_language="la" original_no_xml="Respondi d. Laeto et d. [W]elsero.">Ich habe dem Herrn Laeto und Herrn Welser antwortet.</s>
    <s translated="true" n="17" original_language="la" original_no_xml="Tulit literas Augustam quidam urbis [n]ostrae cursor.">Ein gewisser Läufer unserer Stadt hat die Briefe nach Augsburg gebracht.</s>
    <s translated="true" n="18" original_language="la" original_no_xml="H. Bullingerus tuus.">Dein H. Bullinger.</s>
    <s translated="true" n="19" original_language="la" original_no_xml="Praestantissimo viro d. Ambrosio Blaurero, Constantiensis ecclesiae ministro, fratri charissimo suo.">Dem vortrefflichen Herrn Ambrosius Blaurer, dem Prediger der Kirche von Konstanz, seinem liebsten Bruder.</s>
    <s translated="true" n="20" original_language="la" original_no_xml="Constantz.">Konstantz.</s>
  </letter>
</file>
